tft_loaded_dice/__init__.py
tft_loaded_dice/consts.py
tft_loaded_dice/data.json
tft_loaded_dice/exceptions.py
tft_loaded_dice/main.py
tft_loaded_dice-12.14.0.dist-info/LICENSE
tft_loaded_dice-12.14.0.dist-info/WHEEL
tft_loaded_dice-12.14.0.dist-info/METADATA
tft_loaded_dice-12.14.0.dist-info/RECORD
