Metadata-Version: 2.1
Name: tft-loaded-dice
Version: 12.14.0
Summary: Loaded dice odds for Teamfight Tactics
Home-page: https://github.com/stradivari96/tft-loaded-dice
License: MIT
Keywords: tft,python,teamfight tactics,loaded dice
Author: Xiang Chen
Author-email: xiangchenchen96@gmail.com
Requires-Python: >=3.8,<4.0
Classifier: License :: OSI Approved :: MIT License
Classifier: Programming Language :: Python :: 3
Classifier: Programming Language :: Python :: 3.10
Classifier: Programming Language :: Python :: 3.8
Classifier: Programming Language :: Python :: 3.9
Project-URL: Repository, https://github.com/stradivari96/tft-loaded-dice
